cartesia_line-0.1.11.dist-info/licenses/LICENSE
line/__init__.py
line/bridge.py
line/bus.py
line/call_request.py
line/events.py
line/harness.py
line/harness_types.py
line/routes.py
line/user_bridge.py
line/voice_agent_app.py
line/voice_agent_system.py
line/evals/__init__.py
line/evals/conversation_runner.py
line/evals/similarity_utils.py
line/evals/turn.py
line/nodes/__init__.py
line/nodes/base.py
line/nodes/conversation_context.py
line/nodes/reasoning.py
line/tools/__init__.py
line/tools/system_tools.py
line/tools/tool_types.py
line/utils/__init__.py
line/utils/aio.py
line/utils/dtmf_lookahead_buffer.py
line/utils/gemini_utils.py
line/utils/log_aiter.py
line/utils/openai_utils.py
line/utils/str.py
cartesia_line-0.1.11.dist-info/METADATA
cartesia_line-0.1.11.dist-info/WHEEL
cartesia_line-0.1.11.dist-info/top_level.txt
cartesia_line-0.1.11.dist-info/RECORD
