Metadata-Version: 2.4
Name: cartesia-line
Version: 0.1.11
Summary: Cartesia Voice Agents SDK
Author-email: "Cartesia AI, Inc." <support@cartesia.ai>
License: Apache 2.0
Project-URL: Repository, https://github.com/cartesia-ai/line
Project-URL: Documentation, https://docs.cartesia.ai/line/
Project-URL: Homepage, https://cartesia.ai/agents
Keywords: voice,agents,ai,cartesia
Classifier: Development Status :: 4 - Beta
Classifier: Intended Audience :: Developers
Classifier: License :: OSI Approved :: Apache Software License
Classifier: Operating System :: OS Independent
Classifier: Programming Language :: Python :: 3
Classifier: Programming Language :: Python :: 3.9
Classifier: Programming Language :: Python :: 3.10
Classifier: Programming Language :: Python :: 3.11
Classifier: Programming Language :: Python :: 3.12
Classifier: Programming Language :: Python :: 3.13
Classifier: Topic :: Software Development :: Libraries :: Python Modules
Classifier: Typing :: Typed
Requires-Python: >=3.9
License-File: LICENSE
Requires-Dist: python-dotenv>=1.0.0
Requires-Dist: loguru>=0.7.0
Requires-Dist: fastapi>=0.115.0
Requires-Dist: aiohttp>=3.8.0
Requires-Dist: pydantic<3,>=2.0.0
Requires-Dist: uvicorn<1,>=0.35.0
Provides-Extra: dev
Requires-Dist: pytest; extra == "dev"
Requires-Dist: pytest-asyncio; extra == "dev"
Requires-Dist: pytest-cov; extra == "dev"
Requires-Dist: pytest-xdist==3.8.0; extra == "dev"
Requires-Dist: pytest-repeat==0.9.4; extra == "dev"
Requires-Dist: pre-commit; extra == "dev"
Requires-Dist: ruff==0.12.8; extra == "dev"
Requires-Dist: google-genai<2,>=1.26.0; extra == "dev"
Provides-Extra: gemini
Requires-Dist: google-genai<2,>=1.26.0; python_version >= "3.9" and extra == "gemini"
Requires-Dist: aiohttp>=3.12.0; extra == "gemini"
Provides-Extra: openai
Requires-Dist: openai>=1.70.0; extra == "openai"
Dynamic: license-file
